{
    "beamType.title": "Сноп",
    "intensitySlider.wiggleMe.text": "придвижи плъзгача",
    "bulbType.monochromatic": "Монохроматична",
    "filterSlider.label": "Цвят на филтъра",
    "RgbBulbsModule.title": "Червена-Зелена-Синя лампи",
    "filterSlider.wiggleMe.text": "придвижи плъзгача",
    "bulbType.white": "бяла",
    "beamType.photons": "фотони",
    "color-vision.name": "Цветно зрение",
    "bulbType.title": "Тип на лампата",
    "bulbSlider.label": "Цвят на лампата",
    "SingleBulbModule.title": "Единична лампа",
    "beamType.solid": "непрекъснат"
}